YamlLib/__init__.py
YamlLib/edityaml.py
YamlLib/error.py
YamlLib/version.py
robotframework_ymllib-0.0.7.dist-info/LICENSE
robotframework_ymllib-0.0.7.dist-info/METADATA
robotframework_ymllib-0.0.7.dist-info/WHEEL
robotframework_ymllib-0.0.7.dist-info/top_level.txt
robotframework_ymllib-0.0.7.dist-info/RECORD
