Metadata-Version: 2.1
Name: robotframework-ymllib
Version: 0.0.7
Summary: A Robot Framework library for Yaml files
Home-page: UNKNOWN
Author: Grazia D'Amico
Author-email: graziagdamico@gmail.com
License: MIT
Keywords: robotframework library yaml yml
Platform: UNKNOWN
Classifier: Programming Language :: Python :: 3
Classifier: Programming Language :: Python :: 2
Classifier: License :: OSI Approved :: MIT License
Classifier: Operating System :: OS Independent
Requires-Python: >=2.7
Requires-Dist: PyYAML
